hydrilla/__init__.py
hydrilla/server/__init__.py
hydrilla/server/__main__.py
hydrilla/server/_version.py
hydrilla/server/config.json
hydrilla/server/config.py
hydrilla/server/serve.py
hydrilla/server/locales/en_US/LC_MESSAGES/hydrilla-messages.mo
hydrilla/server/locales/en_US/LC_MESSAGES/hydrilla-messages.po
hydrilla/server/locales/en_US/LC_MESSAGES/messages.mo
hydrilla/server/locales/en_US/LC_MESSAGES/messages.po
hydrilla/server/templates/base.html
hydrilla/server/templates/index.html
hydrilla-1.0.dist-info/COPYING
hydrilla-1.0.dist-info/METADATA
hydrilla-1.0.dist-info/WHEEL
hydrilla-1.0.dist-info/entry_points.txt
hydrilla-1.0.dist-info/top_level.txt
hydrilla-1.0.dist-info/RECORD
