Metadata-Version: 2.1
Name: hydrilla
Version: 1.0
Summary: Hydrilla repository server
Home-page: https://git.koszko.org/pydrilla
Author: Wojtek Kosior
Author-email: koszko@koszko.org
License: AGPL-3.0-or-later
Project-URL: Bug Tracker, https://hydrillabugs.koszko.org/projects/hydrilla
Keywords: hydrilla,haketilo
Platform: UNKNOWN
Classifier: Development Status :: 4 - Beta
Classifier: Intended Audience :: Developers
Classifier: Environment :: Web Environment
Classifier: Environment :: Console
Classifier: Topic :: Internet :: WWW/HTTP :: WSGI
Classifier: License :: OSI Approved :: GNU Affero General Public License v3 or later (AGPLv3+)
Classifier: Natural Language :: English
Classifier: Operating System :: OS Independent
Classifier: Programming Language :: Python :: 3 :: Only
Requires-Python: >=3.7
Requires-Dist: flask
Requires-Dist: hydrilla.builder (==1.0)
Requires-Dist: jsonschema (>=3.0)
Provides-Extra: setup
Requires-Dist: setuptools-scm ; extra == 'setup'
Provides-Extra: test
Requires-Dist: pytest ; extra == 'test'
